argparse_node/__init__.py
argparse_node-0.0.3.dist-info/METADATA
argparse_node-0.0.3.dist-info/WHEEL
argparse_node-0.0.3.dist-info/top_level.txt
argparse_node-0.0.3.dist-info/RECORD
