Metadata-Version: 2.1
Name: argparse-node
Version: 0.0.3
Summary: A minimal multi-level argument parser for your Python cli apps.
Home-page: https://github.com/enhuiz/argparse_node
Author: enhuiz
Author-email: niuzhe.nz@outlook.com
License: UNKNOWN
Platform: UNKNOWN
Requires-Python: >=3.7.0
Requires-Dist: anytree
